{"manufacturer":"NVIDIA","geforce-rtx-3090-fe":{"name":"GeForce RTX 3090 FE","price":1499,"memoryInterface":384,"vram":24576,"vramType":"GDDR6X","powerConnectors":"8+8","tdp":350,"imageUrl":"https://www.nvidia.com/content/dam/en-zz/Solutions/geforce/ampere/rtx-3090/geforce-rtx-3090-shop-600-p@2x.png"},"geforce-rtx-3080-ti-fe":{"name":"GeForce RTX 3080 Ti FE","price":1199,"memoryInterface":384,"vram":12288,"vramType":"GDDR6X","powerConnectors":"8+8","tdp":350,"imageUrl":"https://media.discordapp.net/attachments/855483403842748437/855483885512294420/GraphicsCard_V1-scaled-removebg-preview.png?width=532&height=300"},"geforce-rtx-3080-fe":{"name":"GeForce RTX 3080 FE","price":699,"memoryInterface":320,"vram":10240,"vramType":"GDDR6X","powerConnectors":"8+8","tdp":320,"imageUrl":"https://www.notebookcheck.net/fileadmin/Notebooks/NVIDIA/geforce_rtx_3080_fe.png"},"geforce-rtx-3070-ti-fe":{"name":"GeForce RTX 3070 Ti FE","price":599,"memoryInterface":256,"vram":8192,"vramType":"GDDR6X","powerConnectors":"8+8","tdp":290,"imageUrl":"https://media.discordapp.net/attachments/855483403842748437/855488342648815656/image-removebg-preview_3.png?width=512&height=312"},"geforce-rtx-3070-fe":{"name":"GeForce RTX 3070 FE","price":499,"memoryInterface":256,"vram":8192,"vramType":"GDDR6","powerConnectors":"8","tdp":220,"imageUrl":"https://www.nvidia.com/content/dam/en-zz/Solutions/geforce/ampere/rtx-3070/geforce-rtx-3070-shop-600-p@2x.png"},"geforce-rtx-3060-ti-fe":{"name":"GeForce RTX 3060 Ti FE","price":399,"memoryInterface":256,"vram":8192,"vramType":"GDDR6","powerConnectors":"8","tdp":200,"imageUrl":"https://papahardware.net/admin/media/videocard/lg/rtx-3060-ti-fe.png"},"geforce-rtx-3060":{"name":"GeForce RTX 3060","price":329,"memoryInterface":192,"vram":12288,"vramType":"GDDR6","powerConnectors":"8","tdp":170},"geforce-rtx-2080-ti-fe":{"name":"GeForce RTX 2080 Ti FE","price":1199,"memoryInterface":352,"vram":11264,"vramType":"GDDR6","powerConnectors":"8+8","tdp":260,"imageUrl":"https://hexus.net/media/uploaded/2018/9/14041b14-b2dd-470c-8cd6-dd71aaaf42fa.png"},"geforce-rtx-2080-super-fe":{"name":"GeForce RTX 2080 Super FE","price":699,"memoryInterface":256,"vram":8192,"vramType":"GDDR6","powerConnectors":"8+6","tdp":250,"imageUrl":"https://www.nvidia.com/content/dam/en-zz/Solutions/geforce/graphic-cards/rtx-2080-super/geforce-rtx-2080-super-shop-P@2x.png"},"geforce-rtx-2080-fe":{"name":"GeForce RTX 2080 FE","price":699,"memoryInterface":256,"vram":8192,"vramType":"GDDR6","powerConnectors":"8+6","tdp":225,"imageUrl":"https://cdn.discordapp.com/attachments/855483403842748437/855490083104751616/6291648_sd-removebg-preview.png"},"geforce-rtx-2070-super-fe":{"name":"GeForce RTX 2070 Super FE","price":499,"memoryInterface":256,"vram":8192,"vramType":"GDDR6","powerConnectors":"8+6","tdp":215,"imageUrl":"https://www.nvidia.com/content/dam/en-zz/Solutions/geforce/graphic-cards/rtx-2070-super/geforce-rtx-2070-super-shop-P@2x.png"},"geforce-rtx-2070-fe":{"name":"GeForce RTX 2070 FE","price":499,"memoryInterface":256,"vram":8192,"vramType":"GDDR6","powerConnectors":"8","tdp":185,"imageUrl":"https://media.discordapp.net/attachments/855483403842748437/855490975845449738/image-removebg-preview_4.png"},"geforce-rtx-2060-super-fe":{"name":"GeForce RTX 2060 Super FE","price":399,"memoryInterface":256,"vram":8192,"vramType":"GDDR6","powerConnectors":"8","tdp":175,"imageUrl":"https://www.nvidia.com/content/dam/en-zz/Solutions/geforce/graphic-cards/rtx-2060-super/geforce-rtx-2060-super-shop-P@2x.png"},"geforce-rtx-2060-fe":{"name":"GeForce RTX 2060 FE","price":349,"memoryInterface":192,"vram":6144,"vramType":"GDDR6","powerConnectors":"8","tdp":160,"imageUrl":"https://media.discordapp.net/attachments/855483403842748437/855491754378920006/image-removebg-preview_5.png"},"geforce-gtx-1660-ti":{"name":"GeForce GTX 1660 Ti","price":279,"memoryInterface":192,"vram":6144,"vramType":"GDDR6","powerConnectors":"8","tdp":120},"geforce-gtx-1660-super":{"name":"GeForce GTX 1660 Super","price":229,"memoryInterface":192,"vram":6144,"vramType":"GDDR6","powerConnectors":"8","tdp":125},"geforce-gtx-1660":{"name":"GeForce GTX 1660","price":219,"memoryInterface":192,"vram":6144,"vramType":"GDDR5","powerConnectors":"8","tdp":120},"geforce-gtx-1650-super":{"name":"GeForce GTX 1650 Super","price":169,"memoryInterface":128,"vram":4096,"vramType":"GDDR6","powerConnectors":"6","tdp":100},"geforce-gtx-1650":{"name":"GeForce GTX 1650","price":149,"memoryInterface":128,"vram":4096,"vramType":"GDDR5/GDDR6","powerConnectors":"6","tdp":85},"titan-rtx":{"name":"TITAN RTX","price":2499,"memoryInterface":384,"vram":24576,"vramType":"GDDR6","powerConnectors":"8+8","tdp":280,"imageUrl":"https://www.nvidia.com/content/dam/en-zz/Solutions/titan/titan-rtx/nvidia-titan-rtx-shop-2c50-d@2x.png"},"geforce-gtx-1080-ti-fe":{"name":"GeForce GTX 1080 Ti FE","price":699,"memoryInterface":352,"vram":11264,"vramType":"GDDDR5X","powerConnectors":"8+6","tdp":250,"imageUrl":"https://www.nvidia.com/content/dam/en-zz/Solutions/GeForce/campaigns/10-series/geforce-1080-ti-2c50-D.png"},"geforce-gtx-1080-fe":{"name":"GeForce GTX 1080 FE","price":599,"memoryInterface":256,"vram":8192,"vramType":"GDDR5X","powerConnectors":"8","tdp":180,"imageUrl":"https://www.nvidia.com/content/dam/en-zz/Solutions/GeForce/campaigns/10-series/geforce-1080-D.png"},"geforce-gtx-1070-ti":{"name":"GeForce GTX 1070 Ti FE","price":449,"memoryInterface":256,"vram":8192,"vramType":"GDDR5","powerConnectors":"8","tdp":180,"imageUrl":"https://www.nvidia.com/content/dam/en-zz/Solutions/GeForce/campaigns/10-series/geforce-1070-ti-D.png"},"geforce-gtx-1070":{"name":"GeForce GTX 1070 FE","price":379,"memoryInterface":256,"vram":8192,"vramType":"GDDR5","powerConnectors":"8","tdp":180,"imageUrl":"https://www.nvidia.com/content/dam/en-zz/Solutions/GeForce/campaigns/10-series/geforce-1070-D.png"},"geforce-gtx-1060-fe-3gb":{"name":"GeForce GTX 1060 FE 3GB","price":299,"memoryInterface":192,"vram":3072,"vramType":"GDDR5","powerConnectors":"6","tdp":120,"imageUrl":"https://www.nvidia.com/content/dam/en-zz/Solutions/GeForce/campaigns/10-series/geforce-1060-D.png"},"geforce-gtX-1060-fe-6gb":{"name":"GeForce GTX 1060 FE 6GB","price":299,"memoryInterface":192,"vram":6144,"vramType":"GDDR5","powerConnectors":"6","tdp":120,"imageUrl":"https://www.nvidia.com/content/dam/en-zz/Solutions/GeForce/campaigns/10-series/geforce-1060-D.png"},"geforce-gtx-1050-ti":{"name":"GeForce GTX 1050 Ti","price":139,"memoryInterface":128,"vram":4096,"vramType":"GDDR5","powerConnectors":"N/A","tdp":75},"geforce-gtx-1050-2gb":{"name":"GeForce GTX 1050 2GB","price":109,"memoryInterface":128,"vram":2048,"vramType":"GDDR5","powerConnectors":"N/A","tdp":75},"geforce-gtx-1050-3gb":{"name":"GeForce GTX 1050 3GB","price":109,"memoryInterface":96,"vram":3072,"vramType":"GDDR5","powerConnectors":"N/A","tdp":75},"geforce-gt-1030-g5":{"name":"GeForce GT 1030 G5","price":80,"memoryInterface":64,"vram":2048,"vramType":"GDDR5","powerConnectors":"N/A","tdp":30},"geforce-gt-1030-s4":{"name":"GeForce GT 1030 S4","price":80,"memoryInterface":64,"vram":2048,"vramType":"SDDR4","powerConnectors":"N/A","tdp":30},"geforce-gt-710":{"name":"GeForce GT 710","price":34,"memoryInterface":64,"vram":2048,"vramType":"DDR3","powerConnectors":"N/A","tdp":19},"geforce-gt-210":{"name":"GeForce GT 210","price":45,"memoryInterface":64,"vram":512,"vramType":"DDR3","powerConnectors":"N/A","tdp":31},"geforce-gtx-950-fe":{"name":"GeForce GTX 950 FE","price":"N/A","memoryInterface":128,"vram":2048,"vramType":"GDDR5","powerConnectors":"6","tdp":90,"imageUrl":"https://media.discordapp.net/attachments/748122380383027210/855625771153227796/2747-front.small-removebg-preview.png"},"geforce-gtx-960":{"name":"GeForce GTX 960 FE","price":"N/A","memoryInterface":128,"vram":2048,"vramType":"GDDR5","powerConnectors":"6","tdp":120,"imageUrl":"https://www.nvidia.com/content/dam/en-zz/Solutions/GeForce/campaigns/900-series/desktop-960.png"},"geforce-gtx-970":{"name":"GeForce GTX 970 FE","price":"N/A","memoryInterface":256,"vram":4096,"vramType":"GDDR5","powerConnectors":"6+6","tdp":145,"imageUrl":"https://www.nvidia.com/content/dam/en-zz/Solutions/GeForce/campaigns/900-series/desktop-970.png"},"geforce-gtx-980":{"name":"GeForce GTX 980 FE","price":"N/A","memoryInterface":256,"vram":4096,"vramType":"GDDR5","powerConnectors":"6+6","tdp":165,"imageUrl":"https://www.nvidia.com/content/dam/en-zz/Solutions/GeForce/campaigns/900-series/desktop-980.png"},"geforce-gtx-980-ti":{"name":"GeForce GTX 980 Ti FE","price":"N/A","memoryInterface":384,"vram":6144,"vramType":"GDDR5","powerConnectors":"6+8","tdp":250,"imageUrl":"https://www.nvidia.com/content/dam/en-zz/Solutions/GeForce/campaigns/900-series/desktop-980-ti.png"},"geforce-gtx-645":{"name":"GeForce GTX 645","price":"N/A","memoryInterface":128,"vram":1024,"vramType":"GDDR5","powerConnectors":"N/A","tdp":130},"geforce-gtx-650":{"name":"GeForce GTX 650","price":"N/A","memoryInterface":128,"vram":1024,"vramType":"GDDR5","powerConnectors":"6","tdp":64},"geforce-gtx-650-ti":{"name":"GeForce GTX 650 Ti","price":"N/A","memoryInterface":128,"vram":1024,"vramType":"GDDR5","powerConnectors":"6","tdp":110},"geforce-gtx-650-ti-boost":{"name":"GeForce GTX 650 Ti BOOST","price":"N/A","memoryInterface":192,"vram":2048,"vramType":"GDDR5","powerConnectors":"6","tdp":134},"geforce-gtx-660":{"name":"GeForce GTX 660","price":"N/A","memoryInterface":192,"vram":2048,"vramType":"GDDR5","powerConnectors":"6","tdp":140},"geforce-gtx-660-ti":{"name":"GeForce GTX 660 Ti","price":"N/A","memoryInterface":192,"vram":2048,"vramType":"GDDR5","powerConnectors":"6+6","tdp":150},"geforce-gtx-670":{"name":"GeForce GTX 670","price":"N/A","memoryInterface":256,"vram":2048,"vramType":"GDDR5","powerConnectors":"6+6","tdp":170},"geforce-gtx-680":{"name":"GeForce GTX 680","price":"N/A","memoryInterface":256,"vram":2048,"vramType":"GDDR5","powerConnectors":"6+6","tdp":195},"geforce-gtx-690-fe":{"name":"GeForce GTX 690 FE","price":999,"memoryInterface":512,"vram":4096,"vramType":"GDDR5","powerConnectors":"8+8","tdp":300},"geforce-gtx-750":{"name":"GeForce GTX 750","price":"N/A","memoryInterface":128,"vram":1024,"vramType":"GDDR5","powerConnectors":"N/A","tdp":55},"geforce-gtx-750-ti":{"name":"GeForce GTX 750 Ti","price":"N/A","memoryInterface":128,"vram":2048,"vramType":"GDDR5","powerConnectors":"N/A","tdp":60},"geforce-gtx-760":{"name":"GeForce GTX 760","price":"N/A","memoryInterface":256,"vram":2048,"vramType":"GDDR5","powerConnectors":"6+6","tdp":170},"geforce-gtx-760-ti":{"name":"GeForce GTX 760 Ti","price":"N/A","memoryInterface":256,"vram":2048,"vramType":"GDDR5","powerConnectors":"6+6","tdp":170},"geforce-gtx":{"name":"GeForce GTX","price":"N/A","memoryInterface":256,"vram":2048,"vramType":"GDDR5","powerConnectors":"8+6","tdp":230},"geforce-gtx-780":{"name":"GeForce GTX 780","price":"N/A","memoryInterface":384,"vram":3072,"vramType":"GDDR5","powerConnectors":"8+6","tdp":250},"geforce-gtx-780-ti":{"name":"GeForce GTX 780 Ti","price":"N/A","memoryInterface":384,"vram":3072,"vramType":"GDDR5","powerConnectors":"8+6","tdp":250},"geforce-g100":{"name":"GeForce G100","price":"N/A","memoryInterface":64,"vram":256,"vramType":"DDR2","powerConnectors":"N/A","tdp":35},"geforce-gt-120":{"name":"GeForce GT 120","price":"N/A","memoryInterface":128,"vram":512,"vramType":"DDR2","powerConnectors":"N/A","tdp":50},"geforce-gt-130":{"name":"GeForce GT 130","price":"N/A","memoryInterface":192,"vram":512,"vramType":"DDR2","powerConnectors":"6","tdp":75},"geforce-gt-140":{"name":"GeForce GT 140","price":"N/A","memoryInterface":256,"vram":1024,"vramType":"GDDR3","powerConnectors":"6","tdp":105},"geforce-gt-150":{"name":"GeForce GT 150","price":"N/A","memoryInterface":256,"vram":1024,"vramType":"GDDR3","powerConnectors":"6+6","tdp":141},"geforce-310":{"name":"GeForce 310","price":"N/A","memoryInterface":64,"vram":512,"vramType":"DDR2","powerConnectors":"N/A","tdp":31},"geforce-315-256mb":{"name":"GeForce 315 256MB","price":"N/A","memoryInterface":64,"vram":256,"vramType":"DDR2","powerConnectors":"N/A","tdp":33},"geforce-315-512mb":{"name":"GeForce 315 512MB","price":"N/A","memoryInterface":64,"vram":512,"vramType":"DDR3","powerConnectors":"N/A","tdp":33},"geforce-315-1gb":{"name":"GeForce 315 1GB","price":"N/A","memoryInterface":64,"vram":1024,"vramType":"DDR3","powerConnectors":"N/A","tdp":33},"geforce-gt-320":{"name":"GeForce GT 320","price":"N/A","memoryInterface":128,"vram":1024,"vramType":"GDDR3","powerConnectors":"N/A","tdp":43},"geforce-gt-330-256mb":{"name":"GeForce GT 330 256MB","price":"N/A","memoryInterface":128,"vram":256,"vramType":"DDR2","powerConnectors":"N/A","tdp":75},"geforce-gt-330-512mb":{"name":"GeForce GT 330 512MB","price":"N/A","memoryInterface":128,"vram":512,"vramType":"GDDR3","powerConnectors":"N/A","tdp":75},"geforce-gt-330-1gb":{"name":"GeForce GT 330 1GB","price":"N/A","memoryInterface":256,"vram":1024,"vramType":"GDDR3","powerConnectors":"N/A","tdp":75},"geforce-gt-340-":{"name":"GeForce GT 340 ","price":"N/A","memoryInterface":128,"vram":1024,"vramType":"GDDR3","powerConnectors":"N/A","tdp":69},"geforce-205":{"name":"GeForce 205","price":"N/A","memoryInterface":64,"vram":512,"vramType":"DDR2","powerConnectors":"N/A","tdp":31},"geforce-210-512mb":{"name":"GeForce 210 512MB","price":"N/A","memoryInterface":64,"vram":512,"vramType":"DDR3","powerConnectors":"N/A","tdp":31},"geforce-210-1gb":{"name":"GeForce 210 1GB","price":"N/A","memoryInterface":64,"vram":1024,"vramType":"DDR2","powerConnectors":"N/A","tdp":31},"geforce-210-1gb-rev.-2":{"name":"GeForce 210 1GB Rev. 2","price":"N/A","memoryInterface":64,"vram":1024,"vramType":"DDR3","powerConnectors":"N/A","tdp":31},"geforce-g210-512mb":{"name":"GeForce G210 512MB","price":"N/A","memoryInterface":64,"vram":512,"vramType":"DDR2","powerConnectors":"N/A","tdp":31},"geforce-g210-128mb":{"name":"GeForce G210 128MB","price":"N/A","memoryInterface":64,"vram":128,"vramType":"DDR2","powerConnectors":"N/A","tdp":31},"geforce-gt-220-521mb":{"name":"GeForce GT 220 521MB","price":"N/A","memoryInterface":128,"vram":512,"vramType":"DDR2","powerConnectors":"N/A","tdp":58},"geforce-gt-220-1gb":{"name":"GeForce GT 220 1GB","price":"N/A","memoryInterface":256,"vram":1024,"vramType":"GDDR3","powerConnectors":"N/A","tdp":58},"geforce-gt--230-512mb":{"name":"GeForce GT 230 512MB","price":"N/A","memoryInterface":256,"vram":512,"vramType":"GDDR3","powerConnectors":"N/A","tdp":75},"geforce-gt-230-1.5gb":{"name":"GeForce GT 230 1.5GB","price":"N/A","memoryInterface":192,"vram":1536,"vramType":"DDR2","powerConnectors":"N/A","tdp":75},"geforce-gt-240":{"name":"GeForce GT 240","price":"N/A","memoryInterface":128,"vram":1024,"vramType":"GDDR5","powerConnectors":"N/A","tdp":69},"geforce-gts-250":{"name":"GeForce GTS 250","price":"N/A","memoryInterface":256,"vram":1024,"vramType":"GDDR3","powerConnectors":"6","tdp":150},"geforce-gtx-260-896mb":{"name":"GeForce GTX 260 896MB","price":"N/A","memoryInterface":448,"vram":896,"vramType":"GDDR3","powerConnectors":"6+6","tdp":182},"geforce-gtx-260-1gb":{"name":"GeForce GTX 260 1GB","price":"N/A","memoryInterface":448,"vram":1792,"vramType":"GDDR3","powerConnectors":"6+6","tdp":182},"geforce-gtx-275":{"name":"GeForce GTX 275","price":"N/A","memoryInterface":448,"vram":896,"vramType":"GDDR3","powerConnectors":"6+6","tdp":219},"geforce-gtx-280":{"name":"GeForce GTX 280","price":"N/A","memoryInterface":512,"vram":1024,"vramType":"GDDR3","powerConnectors":"6+8","tdp":236},"geforce-gtx-285":{"name":"GeForce GTX 285","price":"N/A","memoryInterface":512,"vram":1024,"vramType":"GDDR3","powerConnectors":"6+6","tdp":204},"geforce-gtx-295":{"name":"GeForce GTX 295","price":"N/A","memoryInterface":448,"vram":896,"vramType":"GDDR3","powerConnectors":"6+8","tdp":289},"geforce-405-512mb":{"name":"GeForce 405 512MB","price":"N/A","memoryInterface":64,"vram":512,"vramType":"DDR3","powerConnectors":"N/A","tdp":25},"geforce-405-1gb":{"name":"GeForce 405 1GB","price":"N/A","memoryInterface":128,"vram":1024,"vramType":"DDR2","powerConnectors":"N/A","tdp":25},"geforce-gt-415":{"name":"GeForce GT 415","price":"N/A","memoryInterface":128,"vram":512,"vramType":"DDR3","powerConnectors":"N/A","tdp":32},"geforce-gt-420":{"name":"GeForce GT 420","price":"N/A","memoryInterface":128,"vram":1024,"vramType":"DDR3","powerConnectors":"N/A","tdp":50},"geforce-gt-430-512mb":{"name":"GeForce GT 430 512MB","price":"N/A","memoryInterface":64,"vram":512,"vramType":"DDR3","powerConnectors":"N/A","tdp":49},"geforce-gt-430-2gb":{"name":"GeForce GT 430 2GB","price":"N/A","memoryInterface":128,"vram":2048,"vramType":"DDR3","powerConnectors":"N/A","tdp":49},"geforce-gt-440":{"name":"GeForce GT 440","price":"N/A","memoryInterface":128,"vram":1024,"vramType":"DDR3","powerConnectors":"N/A","tdp":65},"geforce-gts-450-512mb":{"name":"GeForce GTS 450 512MB","price":"N/A","memoryInterface":128,"vram":511,"vramType":"GDDR5","powerConnectors":"6","tdp":106},"geforce-gts-450-1gb":{"name":"GeForce GTS 450 1GB","price":"N/A","memoryInterface":128,"vram":1024,"vramType":"GDDR5","powerConnectors":"6","tdp":106},"geforce-gtx-460-700mb":{"name":"GeForce GTX 460 700MB","price":"N/A","memoryInterface":192,"vram":768,"vramType":"GDDR5","powerConnectors":"N/A","tdp":160},"geforce-gtx-460-1gb":{"name":"GeForce GTX 460 1GB","price":"N/A","memoryInterface":256,"vram":1024,"vramType":"GDDR5","powerConnectors":"6+6","tdp":150},"geforce-gtx-465":{"name":"GeForce GTX 465","price":"N/A","memoryInterface":256,"vram":1024,"vramType":"GDDR5","powerConnectors":"6+6","tdp":200},"geforce-gtx-470":{"name":"GeForce GTX 470","price":"N/A","memoryInterface":320,"vram":1280,"vramType":"GDDR5","powerConnectors":"6+6","tdp":215},"geforce-gtx-480":{"name":"GeForce GTX 480","price":"N/A","memoryInterface":384,"vram":1536,"vramType":"GDDR5","powerConnectors":"6+8","tdp":250},"geforce-gtx-490":{"name":"GeForce GTX 490","price":"N/A","memoryInterface":384,"vram":1536,"vramType":"GDDR5","powerConnectors":"8+8","tdp":365},"quadro-rtx-a6000":{"name":"Quadro RTX A6000","price":4650,"memoryInterface":384,"vram":49152,"vramType":"GDDR6","powerConnectors":"8","tdp":300},"quadro-rtx-a5000":{"name":"Quadro RTX A5000","price":"N/A","memoryInterface":384,"vram":24576,"vramType":"GDDR6","powerConnectors":"8","tdp":230},"quadro-rtx-a4000":{"name":"Quadro RTX A4000","price":"N/A","memoryInterface":256,"vram":16384,"vramType":"GDDR6","powerConnectors":"6","tdp":140},"quadro-rtx-8000":{"name":"Quadro RTX 8000","price":10000,"memoryInterface":384,"vram":49152,"vramType":"GDDR6","powerConnectors":"8+6","tdp":295},"quadro-rtx-6000":{"name":"Quadro RTX 6000","price":6300,"memoryInterface":384,"vram":24576,"vramType":"GDDR6","powerConnectors":"8+6","tdp":260},"quadro-rtx-5000":{"name":"Quadro RTX 5000","price":2300,"memoryInterface":256,"vram":16384,"vramType":"GDDR6","powerConnectors":"8+6","tdp":230},"quadro-rtx-4000":{"name":"Quadro RTX 4000","price":900,"memoryInterface":256,"vram":8192,"vramType":"GDDR6","powerConnectors":"8","tdp":160},"quadro-gv-100":{"name":"Quadro GV 100","price":9000,"memoryInterface":4096,"vram":32768,"vramType":"HBM 2","powerConnectors":"8","tdp":250},"quadro-gp-100":{"name":"Quadro GP 100","price":"N/A","memoryInterface":4096,"vram":16384,"vramType":"HBM 2","powerConnectors":"8","tdp":235},"quadro-p6000":{"name":"Quadro P6000","price":6000,"memoryInterface":384,"vram":24576,"vramType":"GDDR5X","powerConnectors":"8","tdp":250},"quadro-p5000":{"name":"Quadro P5000","price":2500,"memoryInterface":256,"vram":16348,"vramType":"GDDR5X","powerConnectors":"8","tdp":180},"quadro-p4000":{"name":"Quadro P4000","price":815,"memoryInterface":256,"vram":8192,"vramType":"GDDR5","powerConnectors":"6","tdp":105},"quadro-p2200":{"name":"Quadro P2200","price":"N/A","memoryInterface":160,"vram":5120,"vramType":"GDDR5X","powerConnectors":"N/A","tdp":75},"quadro-p2000":{"name":"Quadro P2000","price":"N/A","memoryInterface":160,"vram":5120,"vramType":"GDDR5","powerConnectors":"N/A","tdp":75},"quadro-p1000":{"name":"Quadro P1000","price":"N/A","memoryInterface":128,"vram":4096,"vramType":"GDDR5","powerConnectors":"N/A","tdp":47},"quadro-p620":{"name":"Quadro P620","price":"N/A","memoryInterface":128,"vram":2048,"vramType":"GDDR5","powerConnectors":"N/A","tdp":40},"quadro-p600":{"name":"Quadro P600","price":"N/A","memoryInterface":128,"vram":2048,"vramType":"GDDR5","powerConnectors":"N/A","tdp":40},"quadro-p400":{"name":"Quadro P400","price":"N/A","memoryInterface":64,"vram":2048,"vramType":"GDDR5","powerConnectors":"N/A","tdp":30},"quadro-m6000-24gb":{"name":"Quadro M6000 24GB","price":7400,"memoryInterface":384,"vram":24576,"vramType":"GDDR5 ECC","powerConnectors":"8","tdp":250},"quadro-m6000-12gb":{"name":"Quadro M6000 12GB","price":"N/A","memoryInterface":384,"vram":12288,"vramType":"GDDR5 ECC","powerConnectors":"8","tdp":250},"quadro-m5000":{"name":"Quadro M5000","price":3400,"memoryInterface":256,"vram":8192,"vramType":"GDDR5 ECC","powerConnectors":"6","tdp":150},"quadro-m4000":{"name":"Quadro M4000","price":2150,"memoryInterface":256,"vram":8192,"vramType":"GDDR5","powerConnectors":"6","tdp":120},"quadro-m2000":{"name":"Quadro M2000","price":"N/A","memoryInterface":128,"vram":4096,"vramType":"GDDR5","powerConnectors":"N/A","tdp":75},"quadro-k6000":{"name":"Quadro K6000","price":5270,"memoryInterface":384,"vram":12288,"vramType":"GDDR5 ECC","powerConnectors":"6+6","tdp":225},"quadro-k5200":{"name":"Quadro K5200","price":"N/A","memoryInterface":256,"vram":8192,"vramType":"GDDR5 ECC","powerConnectors":"6","tdp":150},"quadro-k5000":{"name":"Quadro K5000","price":2500,"memoryInterface":256,"vram":4096,"vramType":"GDDR5 ECC","powerConnectors":"6","tdp":122},"quadro-k4200":{"name":"Quadro K4200","price":"N/A","memoryInterface":256,"vram":4096,"vramType":"GDDR5","powerConnectors":"6","tdp":108},"quadro-k4000":{"name":"Quadro K4000","price":1270,"memoryInterface":192,"vram":3072,"vramType":"GDDR5","powerConnectors":"6","tdp":80},"quadro-k2200":{"name":"Quadro K2200","price":"N/A","memoryInterface":128,"vram":4096,"vramType":"GDDR5","powerConnectors":"N/A","tdp":68},"quadro-k2000":{"name":"Quadro k2000","price":600,"memoryInterface":128,"vram":2048,"vramType":"GDDR5","powerConnectors":"N/A","tdp":51},"quadro-k1200":{"name":"Quadro K1200","price":"N/A","memoryInterface":128,"vram":4096,"vramType":"GDDR5","powerConnectors":"N/A","tdp":45},"quadro-k620":{"name":"Quadro k620","price":"N/A","memoryInterface":128,"vram":2048,"vramType":"GDDR3","powerConnectors":"N/A","tdp":45},"quadro-k600":{"name":"Quadro K600","price":200,"memoryInterface":128,"vram":1024,"vramType":"GDDR3","powerConnectors":"N/A","tdp":41},"quadro-410":{"name":"Quadro 410","price":150,"memoryInterface":64,"vram":512,"vramType":"DDR3","powerConnectors":"N/A","tdp":38},"quadro-k420":{"name":"Quadro K420","price":"N/A","memoryInterface":128,"vram":1024,"vramType":"GDDR3","powerConnectors":"N/A","tdp":41},"quadro-7000":{"name":"Quadro 7000","price":14500,"memoryInterface":384,"vram":6144,"vramType":"GDDR5 ECC","powerConnectors":"8+6","tdp":204},"quadro-6000":{"name":"Quadro 6000","price":4400,"memoryInterface":384,"vram":6144,"vramType":"GDDR5 ECC","powerConnectors":"8+6","tdp":204},"quadro-5000":{"name":"Quadro 5000","price":2500,"memoryInterface":320,"vram":2560,"vramType":"GDDR5 ECC","powerConnectors":"8","tdp":152},"quadro-4000":{"name":"Quadro 4000","price":1200,"memoryInterface":256,"vram":2048,"vramType":"GDDR5","powerConnectors":"6","tdp":142},"quadro-2000":{"name":"Quadro 2000","price":600,"memoryInterface":128,"vram":1024,"vramType":"GDDR5","powerConnectors":"N/A","tdp":62},"quadro-plex-7000-(two-7000s-in-a-box)":{"name":"Quadro Plex 7000 (two 7000s in a box)","price":15000,"memoryInterface":384,"vram":6144,"vramType":"GDDR5 ECC","powerConnectors":"N/A","tdp":600},"quadro-600":{"name":"Quadro 600","price":179,"memoryInterface":128,"vram":1024,"vramType":"GDDR3","powerConnectors":"N/A","tdp":40},"quadro-400":{"name":"Quadro 400","price":169,"memoryInterface":64,"vram":512,"vramType":"GDDR3","powerConnectors":"N/A","tdp":32},"quadro-fx-4000-gddr3":{"name":"Quadro FX 4000 GDDR3","price":5000,"memoryInterface":256,"vram":256,"vramType":"GDDR3","powerConnectors":"6","tdp":150},"quadro-fx-3000":{"name":"Quadro FX 3000","price":"N/A","memoryInterface":256,"vram":256,"vramType":"DDR","powerConnectors":"Molex","tdp":"N/A"},"quadro-fx-2000":{"name":"Quadro FX 2000","price":"N/A","memoryInterface":128,"vram":128,"vramType":"GDDR2","powerConnectors":"Molex","tdp":"N/A"},"quadro-fx-1100":{"name":"Quadro FX 1100","price":"N/A","memoryInterface":128,"vram":128,"vramType":"DDR","powerConnectors":"Molex","tdp":"N/A"},"quadro-fx-1000":{"name":"Quadro FX 1000","price":"N/A","memoryInterface":128,"vram":128,"vramType":"GDDR2","powerConnectors":"Molex","tdp":"N/A"},"quadro-fx-700":{"name":"Quadro FX 700","price":"N/A","memoryInterface":128,"vram":128,"vramType":"DDR","powerConnectors":"Molex","tdp":"N/A"},"quadro-fx-500":{"name":"Quadro FX 500","price":"N/A","memoryInterface":128,"vram":128,"vramType":"DDR","powerConnectors":"Molex","tdp":"N/A"},"quadro-4-980xgl":{"name":"Quadro 4 980XGL","price":"N/A","memoryInterface":128,"vram":128,"vramType":"DDR","powerConnectors":"N/A","tdp":"N/A"},"quadro-4-900xgl":{"name":"Quadro 4 900XGL","price":"N/A","memoryInterface":128,"vram":128,"vramType":"DDR","powerConnectors":"N/A","tdp":"N/A"},"quadro-4-780xgl":{"name":"Quadro 4 780XGL","price":"N/A","memoryInterface":128,"vram":128,"vramType":"DDR","powerConnectors":"N/A","tdp":"N/A"},"quadro-4-750xgl":{"name":"Quadro 4 750XGL","price":"N/A","memoryInterface":128,"vram":128,"vramType":"DDR","powerConnectors":"N/A","tdp":"N/A"},"quadro-4-700xgl":{"name":"Quadro 4 700XGL","price":"N/A","memoryInterface":128,"vram":64,"vramType":"DDR","powerConnectors":"N/A","tdp":"N/A"},"quadro-4-580xgl":{"name":"Quadro 4 580XGL","price":"N/A","memoryInterface":128,"vram":64,"vramType":"DDR","powerConnectors":"N/A","tdp":"N/A"},"quadro-4-550xgl":{"name":"Quadro 4 550XGL","price":"N/A","memoryInterface":128,"vram":64,"vramType":"DDR","powerConnectors":"N/A","tdp":"N/A"},"quadro-4-500xgl":{"name":"Quadro 4 500XGL","price":"N/A","memoryInterface":128,"vram":128,"vramType":"SDR","powerConnectors":"N/A","tdp":"N/A"},"quadro-4-380xgl":{"name":"Quadro 4 380XGL","price":"N/A","memoryInterface":128,"vram":64,"vramType":"DDR","powerConnectors":"N/A","tdp":"N/A"},"quadro-dcc":{"name":"Quadro DCC","price":"N/A","memoryInterface":128,"vram":64,"vramType":"DDR","powerConnectors":"N/A","tdp":"N/A"},"quadro-2-mxr":{"name":"Quadro 2 MXR","price":"N/A","memoryInterface":128,"vram":32,"vramType":"SDR","powerConnectors":"N/A","tdp":"N/A"},"quadro-2-pro":{"name":"Quadro 2 Pro","price":"N/A","memoryInterface":128,"vram":64,"vramType":"DDR","powerConnectors":"N/A","tdp":"N/A"},"quadro":{"name":"Quadro","price":"N/A","memoryInterface":128,"vram":32,"vramType":"SDR","powerConnectors":"N/A","tdp":"N/A"},"quadro-fx-5500":{"name":"Quadro FX 5500","price":3000,"memoryInterface":256,"vram":1024,"vramType":"GDDR3","powerConnectors":"6","tdp":96},"quadro-fx-4500x2":{"name":"Quadro FX 4500x2","price":2800,"memoryInterface":256,"vram":512,"vramType":"GDDR3","powerConnectors":"6+6","tdp":145},"quadro-fx-4500":{"name":"Quadro FX 4500","price":2500,"memoryInterface":256,"vram":512,"vramType":"GDDR3","powerConnectors":"6","tdp":109},"quadro-fx-4400":{"name":"Quadro FX 4400","price":2400,"memoryInterface":256,"vram":512,"vramType":"GDDR3","powerConnectors":"6","tdp":83},"quadro-fx-4000-gddr3-molex":{"name":"Quadro FX 4000 GDDR3 Molex","price":2200,"memoryInterface":256,"vram":256,"vramType":"GDDR3","powerConnectors":"Molex+Molex","tdp":142},"quadro-fx-3500":{"name":"Quadro FX 3500","price":1600,"memoryInterface":256,"vram":256,"vramType":"GDDR3","powerConnectors":"N/A","tdp":80},"quadro-fx-3450":{"name":"Quadro FX 3450","price":"N/A","memoryInterface":256,"vram":256,"vramType":"GDDR3","powerConnectors":"6","tdp":83},"quadro-fx-3400":{"name":"Quadro FX 3400","price":"N/A","memoryInterface":256,"vram":256,"vramType":"GDDR3","powerConnectors":"6","tdp":101},"quadro-fx-1500":{"name":"Quadro FX 1500","price":800,"memoryInterface":256,"vram":256,"vramType":"GDDR3","powerConnectors":"N/A","tdp":65},"quadro-fx-1400-":{"name":"Quadro FX 1400 ","price":700,"memoryInterface":256,"vram":128,"vramType":"DDR","powerConnectors":"N/A","tdp":55},"quadro-fx-1300":{"name":"Quadro FX 1300","price":600,"memoryInterface":256,"vram":128,"vramType":"DDR","powerConnectors":"N/A","tdp":55},"quadro-fx-560":{"name":"Quadro FX 560","price":300,"memoryInterface":128,"vram":128,"vramType":"GDDR3","powerConnectors":"N/A","tdp":30},"quadro-fx-550":{"name":"Quadro FX 550","price":"N/A","memoryInterface":128,"vram":128,"vramType":"GDDR3","powerConnectors":"N/A","tdp":30},"quadro-fx-540":{"name":"Quadro FX 540","price":300,"memoryInterface":128,"vram":128,"vramType":"GDDR3","powerConnectors":"N/A","tdp":25},"quadro-fx-350":{"name":"Quadro FX 350","price":"N/A","memoryInterface":64,"vram":128,"vramType":"DDR2","powerConnectors":"N/A","tdp":21},"quadro-fx-330":{"name":"Quadro FX 330","price":"N/A","memoryInterface":64,"vram":64,"vramType":"DDR2","powerConnectors":"N/A","tdp":21},"quadro-vx-200":{"name":"Quadro VX 200","price":"N/A","memoryInterface":256,"vram":512,"vramType":"GDDR3","powerConnectors":"6","tdp":75},"quadro-cx":{"name":"Quadro CX","price":2000,"memoryInterface":384,"vram":1536,"vramType":"GDDR3 ","powerConnectors":"6","tdp":150},"quadro-fx-5800":{"name":"Quadro FX 5800","price":3500,"memoryInterface":512,"vram":4096,"vramType":"GDDR3","powerConnectors":"8+6","tdp":189},"quadro-fx-4800":{"name":"Quadro FX 4800","price":1800,"memoryInterface":384,"vram":1536,"vramType":"GDDR3","powerConnectors":"6","tdp":150},"quadro-fx-5600":{"name":"Quadro FX 5600","price":3000,"memoryInterface":384,"vram":1536,"vramType":"GDDR3","powerConnectors":"6+6","tdp":171},"quadro-fx-4700x2":{"name":"Quadro FX 4700x2","price":3000,"memoryInterface":256,"vram":512,"vramType":"GDDR3","powerConnectors":"8+6","tdp":226},"quadro-fx-4600":{"name":"Quadro FX 4600","price":2000,"memoryInterface":384,"vram":768,"vramType":"GDDR3","powerConnectors":"6","tdp":134},"quadro-fx-3800":{"name":"Quadro FX 3800","price":800,"memoryInterface":256,"vram":1024,"vramType":"GDDR3","powerConnectors":"6","tdp":108},"quadro-fx-3700":{"name":"Quadro FX 3700","price":1600,"memoryInterface":256,"vram":512,"vramType":"GDDR3","powerConnectors":"6","tdp":78},"quadro-fx-1800":{"name":"Quadro FX 1800","price":489,"memoryInterface":192,"vram":768,"vramType":"GDDR3","powerConnectors":"N/A","tdp":59},"quadro-fx-1700":{"name":"Quadro fx 1700","price":700,"memoryInterface":256,"vram":512,"vramType":"DDR2","powerConnectors":"N/A","tdp":42},"quadro-fx-580":{"name":"Quadro FX 580","price":200,"memoryInterface":128,"vram":512,"vramType":"GDDR3","powerConnectors":"N/A","tdp":40},"quadro-fx-570":{"name":"Quadro FX 570","price":200,"memoryInterface":128,"vram":256,"vramType":"DDR2","powerConnectors":"N/A","tdp":38},"quadro-fx-380":{"name":"Quadro FX 380","price":130,"memoryInterface":128,"vram":256,"vramType":"GDDR3","powerConnectors":"N/A","tdp":34},"quadro-fx-370":{"name":"Quadro FX 370","price":130,"memoryInterface":64,"vram":256,"vramType":"DDR2","powerConnectors":"N/A","tdp":35},"quadro-nvs-810-x2":{"name":"Quadro NVS 810 x2","price":"N/A","memoryInterface":64,"vram":2048,"vramType":"DDR3","powerConnectors":"N/A","tdp":68},"quadro-nvs-510":{"name":"Quadro NVS 510","price":450,"memoryInterface":128,"vram":2048,"vramType":"DDR3","powerConnectors":"N/A","tdp":35},"quadro-nvs-315":{"name":"Quadro NVS 315","price":160,"memoryInterface":64,"vram":1024,"vramType":"DDR3","powerConnectors":"N/A","tdp":19},"quadro-nvs-310":{"name":"Quadro NVS 310","price":160,"memoryInterface":64,"vram":512,"vramType":"DDR3","powerConnectors":"N/A","tdp":20},"quadro-nvs-300":{"name":"Quadro NVS 300","price":110,"memoryInterface":64,"vram":512,"vramType":"DDR3","powerConnectors":"N/A","tdp":18},"quadro-nvs-450-x2":{"name":"Quadro NVS 450 x2","price":"N/A","memoryInterface":64,"vram":256,"vramType":"GDDR3","powerConnectors":"N/A","tdp":35},"quadro-nvs-440-x2":{"name":"Quadro NVS 440 x2","price":"N/A","memoryInterface":128,"vram":128,"vramType":"GDDR3","powerConnectors":"N/A","tdp":31},"quadro-nvs-420-x2":{"name":"Quadro NVS 420 x2","price":"N/A","memoryInterface":64,"vram":256,"vramType":"GDDR3","powerConnectors":"N/A","tdp":40},"quadro-nvs-400-x2":{"name":"Quadro NVS 400 x2","price":"N/A","memoryInterface":128,"vram":64,"vramType":"DDR","powerConnectors":"N/A","tdp":18},"quadro-nvs-295-":{"name":"Quadro NVS 295 ","price":"N/A","memoryInterface":64,"vram":256,"vramType":"GDDR3","powerConnectors":"N/A","tdp":23},"quadro-nvs-290":{"name":"Quadro NVS 290","price":150,"memoryInterface":64,"vram":256,"vramType":"DDR2","powerConnectors":"N/A","tdp":21},"quadro-nvs-285":{"name":"Quadro NVS 285","price":"N/A","memoryInterface":64,"vram":128,"vramType":"DDR2","powerConnectors":"N/A","tdp":18},"quadro-nvs-280":{"name":"Quadro NVS 280","price":"N/A","memoryInterface":64,"vram":64,"vramType":"DDR","powerConnectors":"N/A","tdp":13},"quadro-nvs-200":{"name":"Quadro NVS 200","price":"N/A","memoryInterface":128,"vram":64,"vramType":"DDR","powerConnectors":"N/A","tdp":11},"quadro-4-nvs-100":{"name":"Quadro 4 NVS 100","price":"N/A","memoryInterface":128,"vram":64,"vramType":"DDR","powerConnectors":"N/A","tdp":10},"quadro-nvs-50":{"name":"Quadro NVS 50","price":"N/A","memoryInterface":64,"vram":64,"vramType":"DDR","powerConnectors":"N/A","tdp":10},"quadro-fx-600":{"name":"Quadro FX 600","price":"N/A","memoryInterface":128,"vram":128,"vramType":"DDR","powerConnectors":"N/A","tdp":"N/A"},"tesla-c870":{"name":"Tesla C870","price":1500,"memoryInterface":384,"vram":1536,"vramType":"GDDR3","powerConnectors":"6+6","tdp":171},"tesla-c1060":{"name":"Tesla C1060","price":"N/A","memoryInterface":512,"vram":4096,"vramType":"GDDR3","powerConnectors":"8+6","tdp":188},"tesla-c2050":{"name":"Tesla C2050","price":"N/A","memoryInterface":384,"vram":3072,"vramType":"GDDR5","powerConnectors":"8+6","tdp":238},"tesla-m2050":{"name":"Tesla M2050","price":2700,"memoryInterface":384,"vram":3072,"vramType":"GDDR5","powerConnectors":"8+6","tdp":225},"tesla-c2070":{"name":"Tesla C2070","price":"N/A","memoryInterface":384,"vram":6144,"vramType":"GDDR5","powerConnectors":"8","tdp":238},"tesla-c2075":{"name":"Tesla C2075","price":"N/A","memoryInterface":384,"vram":6144,"vramType":"GDDR5","powerConnectors":"8+6","tdp":247},"tesla-m2070":{"name":"Tesla M2070","price":3100,"memoryInterface":384,"vram":6144,"vramType":"GDDR5","powerConnectors":"8+6","tdp":225},"tesla-m2090":{"name":"Tesla M2090","price":"N/A","memoryInterface":384,"vram":6144,"vramType":"GDDR5","powerConnectors":"8+6","tdp":250},"tesla-k10-x2":{"name":"Tesla K10 x2","price":5100,"memoryInterface":256,"vram":4096,"vramType":"GDDR5","powerConnectors":"8+6","tdp":225},"tesla-k20":{"name":"Tesla K20","price":3200,"memoryInterface":320,"vram":5120,"vramType":"GDDR5","powerConnectors":"8+6","tdp":225},"tesla-k20x":{"name":"Tesla K20X","price":7700,"memoryInterface":384,"vram":6144,"vramType":"GDDR5","powerConnectors":"8+6","tdp":235},"tesla-k40":{"name":"Tesla k40","price":7700,"memoryInterface":384,"vram":12288,"vramType":"GDDR5","powerConnectors":"8+6","tdp":245},"tesla-k80-x2":{"name":"Tesla K80 x2","price":"N/A","memoryInterface":384,"vram":12288,"vramType":"GDDR5","powerConnectors":"8","tdp":300},"tesla-m4":{"name":"Tesla M4","price":"N/A","memoryInterface":128,"vram":4096,"vramType":"GDDR5","powerConnectors":"N/A","tdp":50},"tesla-m6":{"name":"Tesla M6","price":"N/A","memoryInterface":256,"vram":8192,"vramType":"GDDR5","powerConnectors":"N/A","tdp":100},"tesla-m10-x4":{"name":"Tesla M10 x4","price":"N/A","memoryInterface":128,"vram":8192,"vramType":"GDDR5","powerConnectors":"8","tdp":225},"tesla-m40":{"name":"Tesla M40","price":"N/A","memoryInterface":384,"vram":12288,"vramType":"GDDR5","powerConnectors":"8+6 ","tdp":250},"tesla-m60-x2":{"name":"Tesla M60 x2","price":"N/A","memoryInterface":256,"vram":8192,"vramType":"GDDR5","powerConnectors":"8","tdp":300},"tesla-p4":{"name":"Tesla P4","price":"N/A","memoryInterface":256,"vram":8192,"vramType":"GDDR5","powerConnectors":"N/A","tdp":75},"tesla-p6":{"name":"Tesla P6","price":"N/A","memoryInterface":256,"vram":16384,"vramType":"GDDR5","powerConnectors":"N/A","tdp":90},"tesla-p40":{"name":"Tesla P40","price":5700,"memoryInterface":384,"vram":24576,"vramType":"GDDR5X","powerConnectors":"8+6","tdp":250},"tesla-p100-12gb":{"name":"Tesla P100 12GB","price":4600,"memoryInterface":3072,"vram":12288,"vramType":"HBM2","powerConnectors":"8","tdp":250,"imageUrl":"http://smartcdn.prod.postmedia.digital/driving/wp-content/uploads/2019/04/model-s-001.jpg"},"tesla-p100-16gb":{"name":"Tesla P100 16GB","price":5700,"memoryInterface":4096,"vram":16384,"vramType":"HBM2","powerConnectors":"8","tdp":250,"imageUrl":"http://smartcdn.prod.postmedia.digital/driving/wp-content/uploads/2019/04/model-s-001.jpg"},"tesla-v100":{"name":"Tesla V100","price":"N/A","memoryInterface":4096,"vram":16384,"vramType":"HBM2","powerConnectors":"8+8","tdp":300},"tesla-t4":{"name":"Tesla T4","price":"N/A","memoryInterface":256,"vram":16384,"vramType":"GDDR6","powerConnectors":"N/A","tdp":70},"tesla-a10":{"name":"Tesla A10","price":"N/A","memoryInterface":384,"vram":24576,"vramType":"GDDR6","powerConnectors":"8","tdp":150},"tesla-a16-x4":{"name":"Tesla A16 x4","price":"N/A","memoryInterface":128,"vram":16384,"vramType":"GDDR6","powerConnectors":"8","tdp":250},"tesla-a30":{"name":"Tesla A30","price":"N/A","memoryInterface":3072,"vram":24576,"vramType":"HBM2","powerConnectors":"8","tdp":165},"tesla-a40":{"name":"Tesla A40","price":"N/A","memoryInterface":384,"vram":49152,"vramType":"GDDR6","powerConnectors":"8","tdp":300},"tesla-a100":{"name":"Tesla A100","price":"N/A","memoryInterface":5120,"vram":40960,"vramType":"HBM2e","powerConnectors":"N/A","tdp":400},"quadro-fx-3000g":{"name":"Quadro FX 3000G","price":"N/A","memoryInterface":256,"vram":256,"vramType":"DDR","powerConnectors":"Molex","tdp":"N/A"},"quadro-fx-370-lp":{"name":"Quadro FX 370 LP","price":130,"memoryInterface":64,"vram":256,"vramType":"DDR2","powerConnectors":"N/A","tdp":25},"quadro-fx-380-lp":{"name":"Quadro FX 380 LP","price":170,"memoryInterface":64,"vram":512,"vramType":"GDDR3","powerConnectors":"N/A","tdp":28},"quadro-fx-4400g":{"name":"Quadro FX 4400G","price":3000,"memoryInterface":256,"vram":512,"vramType":"GDDR3","powerConnectors":"6","tdp":83},"quadro-fx-4500-sdi":{"name":"Quadro FX 4500 SDI","price":"N/A","memoryInterface":256,"vram":512,"vramType":"GDDR3","powerConnectors":"6","tdp":116},"quadro-fx-4600-sdi":{"name":"Quadro FX 4600 SDI","price":6000,"memoryInterface":384,"vram":768,"vramType":"GDDR3","powerConnectors":"6","tdp":154},"quadro-fx-5500-sdi":{"name":"Quadro FX 5500 SDI","price":7000,"memoryInterface":256,"vram":1024,"vramType":"GDDR3","powerConnectors":"6","tdp":104},"tesla-pg-506-232":{"name":"Tesla PG 506-232","price":"N/A","memoryInterface":3072,"vram":24576,"vramType":"HBM2","powerConnectors":"8","tdp":165},"tesla-c2090":{"name":"Tesla C2090","price":"N/A","memoryInterface":384,"vram":6144,"vramType":"GDDR5","powerConnectors":"N/A","tdp":250},"tesla-d870-x2":{"name":"Tesla D870 x2","price":7500,"memoryInterface":384,"vram":1536,"vramType":"GDDR3","powerConnectors":"N/A","tdp":520},"tesla-k20s":{"name":"Tesla K20S","price":3200,"memoryInterface":320,"vram":5120,"vramType":"GDDR5","powerConnectors":"N/A","tdp":225},"tesla-k20m":{"name":"Tesla K20M","price":3200,"memoryInterface":320,"vram":5120,"vramType":"GDDR5","powerConnectors":"8+6","tdp":225},"tesla-k40d":{"name":"Tesla K40D","price":7700,"memoryInterface":384,"vram":12288,"vramType":"GDDR5","powerConnectors":"N/A","tdp":245},"tesla-k40m":{"name":"Tesla K40M","price":7700,"memoryInterface":384,"vram":12288,"vramType":"GDDR5","powerConnectors":"N/A","tdp":245},"tesla-k40s":{"name":"Tesla K40S","price":7700,"memoryInterface":384,"vram":12288,"vramType":"GDDR5","powerConnectors":"N/A","tdp":245},"tesla-k40st":{"name":"Tesla K40ST","price":7700,"memoryInterface":384,"vram":12288,"vramType":"GDDR5","powerConnectors":"N/A","tdp":245},"tesla-k40t":{"name":"Tesla K40T","price":7700,"memoryInterface":384,"vram":12288,"vramType":"GDDR5","powerConnectors":"N/A","tdp":245},"tesla-k8":{"name":"Tesla K8","price":"N/A","memoryInterface":256,"vram":8192,"vramType":"GDDR5","powerConnectors":"6","tdp":100},"tesla-m1060":{"name":"Tesla M1060","price":1700,"memoryInterface":512,"vram":2048,"vramType":"GDDR3","powerConnectors":"8+6","tdp":188},"tesla-m2070q":{"name":"Tesla M2070Q","price":5500,"memoryInterface":384,"vram":6144,"vramType":"GDDR5","powerConnectors":"8+6","tdp":225},"tesla-m2075":{"name":"Tesla M2075","price":2400,"memoryInterface":384,"vram":6144,"vramType":"GDDR5","powerConnectors":"8+6","tdp":225},"tesla-p10":{"name":"Tesla P10","price":"N/A","memoryInterface":384,"vram":24576,"vramType":"GDDR5X","powerConnectors":"8","tdp":250},"tesla-p100-dgxs":{"name":"Tesla P100 DGXS","price":"N/A","memoryInterface":4096,"vram":16384,"vramType":"HBM2","powerConnectors":"N/A","tdp":300},"tesla-p100-sxm2":{"name":"Tesla P100 SXM2","price":"N/A","memoryInterface":4096,"vram":16384,"vramType":"HBM2","powerConnectors":"N/A","tdp":300},"tesla-pg-500-216":{"name":"Tesla PG 500-216","price":"N/A","memoryInterface":4096,"vram":32768,"vramType":"HBM2","powerConnectors":"N/A","tdp":250},"tesla-pg-503-216":{"name":"Tesla PG 503-216","price":"N/A","memoryInterface":4096,"vram":32768,"vramType":"HBM2","powerConnectors":"N/A","tdp":250},"tesla-s1070-x4":{"name":"Tesla S1070 x4","price":8000,"memoryInterface":512,"vram":4096,"vramType":"GDDR3","powerConnectors":"N/A","tdp":800},"tesla-s1075-x4":{"name":"Tesla S1075 x4","price":"N/A","memoryInterface":512,"vram":4096,"vramType":"GDDR3","powerConnectors":"N/A","tdp":800},"tesla-s2050-x4":{"name":"Tesla S2050 x4","price":12000,"memoryInterface":384,"vram":4096,"vramType":"GDDR5","powerConnectors":"N/A","tdp":900},"tesla-s870-x4":{"name":"Tesla S870 x4","price":12000,"memoryInterface":384,"vram":1536,"vramType":"GDDR3","powerConnectors":"N/A","tdp":800},"tesla-v100-dgxs-16gb":{"name":"Tesla V100 DGXS 16GB","price":"N/A","memoryInterface":4096,"vram":16384,"vramType":"HBM2","powerConnectors":"N/A","tdp":250},"tesla-v100-dgxs-32gb":{"name":"Tesla V100 DGXS 32GB","price":"N/A","memoryInterface":4096,"vram":32768,"vramType":"HBM2","powerConnectors":"N/A","tdp":250},"tesla-v100-fhhl":{"name":"Tesla V100 FHHL","price":"N/A","memoryInterface":4096,"vram":16384,"vramType":"HBM2","powerConnectors":"8","tdp":250},"tesla-v100-32gb":{"name":"Tesla V100 32GB","price":"N/A","memoryInterface":4096,"vram":32768,"vramType":"HBM2","powerConnectors":"8+8","tdp":250},"tesla-v100-sxm2-16gb":{"name":"Tesla V100 SXM2 16GB","price":"N/A","memoryInterface":4096,"vram":16384,"vramType":"HBM2","powerConnectors":"N/A","tdp":250},"tesla-v100-sxm2-32gb":{"name":"Tesla V100 SXM2 32GB","price":"N/A","memoryInterface":4096,"vram":32768,"vramType":"HBM2","powerConnectors":"N/A","tdp":250},"tesla-v100-smx3-":{"name":"Tesla V100 SMX3 ","price":"N/A","memoryInterface":4096,"vram":32768,"vramType":"HBM2","powerConnectors":"N/A","tdp":250},"tesla-v100s-":{"name":"Tesla v100S ","price":"N/A","memoryInterface":4096,"vram":32768,"vramType":"HBM2","powerConnectors":"8+8","tdp":250},"tesla-x2070":{"name":"Tesla X2070","price":"N/A","memoryInterface":384,"vram":6144,"vramType":"GDDR5","powerConnectors":"N/A","tdp":225},"cmp-30hx":{"name":"CMP 30HX","price":800,"memoryInterface":192,"vram":6144,"vramType":"GDDR6","powerConnectors":"8","tdp":125},"cmp-50hx":{"name":"CMP 50HX","price":"N/A","memoryInterface":320,"vram":10240,"vramType":"GDDR6","powerConnectors":"8+8","tdp":250},"cmp-40hx":{"name":"CMP 40HX","price":700,"memoryInterface":256,"vram":8192,"vramType":"GDDR6","powerConnectors":"8","tdp":185},"cmp-90hx":{"name":"CMP 90HX","price":"N/A","memoryInterface":320,"vram":10240,"vramType":"GDDR6X","powerConnectors":"8+8","tdp":320},"p102-100":{"name":"P102-100","price":"N/A","memoryInterface":320,"vram":5120,"vramType":"GDDR5X","powerConnectors":"8+8","tdp":250},"p102-101":{"name":"P102-101","price":"N/A","memoryInterface":320,"vram":10240,"vramType":"GDDR5","powerConnectors":"8+8","tdp":250},"p104-100":{"name":"P104-100","price":"N/A","memoryInterface":256,"vram":4096,"vramType":"GDDR5X","powerConnectors":"8","tdp":200},"p104-101":{"name":"P104-101","price":"N/A","memoryInterface":256,"vram":4096,"vramType":"GDDR5","powerConnectors":"8","tdp":200},"p106-90":{"name":"P106-90","price":"N/A","memoryInterface":192,"vram":3072,"vramType":"GDDR5","powerConnectors":"6","tdp":75},"p106-100":{"name":"P106-100","price":"N/A","memoryInterface":192,"vram":6144,"vramType":"GDDR5","powerConnectors":"6","tdp":120},"p106m":{"name":"P106M","price":"N/A","memoryInterface":128,"vram":4096,"vramType":"GDDR5","powerConnectors":"N/A","tdp":75},"geforce-505-512mb":{"name":"GeForce 505 512MB","price":"N/A","memoryInterface":64,"vram":512,"vramType":"DDR3","powerConnectors":"N/A","tdp":25},"geforce-505-1gb":{"name":"GeForce 505 1GB","price":"N/A","memoryInterface":128,"vram":1024,"vramType":"DDR3","powerConnectors":"N/A","tdp":25},"geforce-510":{"name":"GeForce 510","price":"N/A","memoryInterface":64,"vram":1024,"vramType":"DDR3","powerConnectors":"N/A","tdp":25},"geforce-gt-520":{"name":"GeForce GT 520","price":"N/A","memoryInterface":64,"vram":1024,"vramType":"DDR3","powerConnectors":"N/A","tdp":29},"geforce-gt-530":{"name":"GeForce GT 530","price":"N/A","memoryInterface":128,"vram":1024,"vramType":"DDR3","powerConnectors":"N/A","tdp":50},"geforce-gt-545":{"name":"GeForce GT 545","price":"N/A","memoryInterface":128,"vram":1024,"vramType":"GDDR5","powerConnectors":"6","tdp":105},"geforce-gtx-550-ti":{"name":"GeForce GTX 550 Ti","price":"N/A","memoryInterface":192,"vram":1024,"vramType":"GDDR5","powerConnectors":"6","tdp":116},"geforce-gtx-555":{"name":"GeForce GTX 555","price":"N/A","memoryInterface":192,"vram":1024,"vramType":"GDDR%","powerConnectors":"6+6","tdp":150},"geforce-gtx-560":{"name":"GeForce GTX 560","price":"N/A","memoryInterface":256,"vram":1024,"vramType":"GDDR5","powerConnectors":"6+6","tdp":150},"geforce-gtx-560-ti":{"name":"GeForce GTX 560 Ti","price":"N/A","memoryInterface":256,"vram":1024,"vramType":"GDDR5","powerConnectors":"6+6","tdp":170},"geforce-gtx-570":{"name":"GeForce GTX 570","price":"N/A","memoryInterface":320,"vram":1280,"vramType":"GDDR5","powerConnectors":"6+6","tdp":219},"geforce-gtx-580":{"name":"GeForce GTX 580","price":"N/A","memoryInterface":384,"vram":1536,"vramType":"GDDR5","powerConnectors":"6+8","tdp":224},"geforce-gtx-590":{"name":"GeForce GTX 590","price":"N/A","memoryInterface":384,"vram":1536,"vramType":"GDDR5","powerConnectors":"8+8","tdp":365},"titan":{"name":"Titan","price":999,"memoryInterface":384,"vram":6144,"vramType":"GDDR5","powerConnectors":"6+8","tdp":250},"titan-black":{"name":"Titan Black","price":999,"memoryInterface":384,"vram":6144,"vramType":"GDDR5 ","powerConnectors":"6+8","tdp":250},"titan-z":{"name":"Titan Z","price":2999,"memoryInterface":768,"vram":12288,"vramType":"GDDR5","powerConnectors":"8+8","tdp":375},"titan-x":{"name":"Titan X","price":999,"memoryInterface":384,"vram":12288,"vramType":"GDDR5","powerConnectors":"6+8","tdp":250},"titan-x-pascal":{"name":"Titan X pascal","price":1199,"memoryInterface":384,"vram":12288,"vramType":"GDDR5X ","powerConnectors":"6+8","tdp":250},"titan-xp":{"name":"Titan Xp","price":1119,"memoryInterface":384,"vram":12228,"vramType":"GDDR5X","powerConnectors":"6+8","tdp":250},"titan-v":{"name":"Titan V","price":2999,"memoryInterface":3072,"vram":12288,"vramType":"HBM2","powerConnectors":"6+8","tdp":250},"titan-v-ceo-edition-":{"name":"Titan V CEO edition ","price":"N/A","memoryInterface":4096,"vram":32768,"vramType":"HBM2","powerConnectors":"6+8","tdp":250}}